whatsextract/__init__.py
whatsextract-1.0.2.dist-info/METADATA
whatsextract-1.0.2.dist-info/WHEEL
whatsextract-1.0.2.dist-info/top_level.txt
whatsextract-1.0.2.dist-info/RECORD
