Metadata-Version: 2.4
Name: whatsextract
Version: 1.0.2
Summary: WhatsExtract Python SDK
Author: WhatsExtract
License: MIT
Project-URL: Homepage, https://example.com
Classifier: Programming Language :: Python :: 3
Classifier: License :: OSI Approved :: MIT License
Classifier: Topic :: Software Development :: Libraries
Requires-Python: >=3.8
Requires-Dist: requests>=2.31.0
Requires-Dist: aiohttp>=3.9.0
Dynamic: requires-python
